LICENSE
MANIFEST.in
README
ez_setup.py
setup.py
tests/run.py
tests/util.py
tests/doctests/test_build_sphinxdocs.rst
tests/documents/sphinxdoc/CHANGES
tests/documents/sphinxdoc/EXAMPLES
tests/documents/sphinxdoc/sphinx-build.py
tests/documents/sphinxdoc/source/Makefile
tests/documents/sphinxdoc/source/builders.rst
tests/documents/sphinxdoc/source/changes.rst
tests/documents/sphinxdoc/source/conf.py
tests/documents/sphinxdoc/source/config.rst
tests/documents/sphinxdoc/source/contents.rst
tests/documents/sphinxdoc/source/domains.rst
tests/documents/sphinxdoc/source/examples.rst
tests/documents/sphinxdoc/source/extensions.rst
tests/documents/sphinxdoc/source/faq.rst
tests/documents/sphinxdoc/source/glossary.rst
tests/documents/sphinxdoc/source/intro.rst
tests/documents/sphinxdoc/source/invocation.rst
tests/documents/sphinxdoc/source/more.png
tests/documents/sphinxdoc/source/rest.rst
tests/documents/sphinxdoc/source/templating.rst
tests/documents/sphinxdoc/source/theming.rst
tests/documents/sphinxdoc/source/tutorial.rst
tests/documents/sphinxdoc/source/_static/sphinx.png
tests/documents/sphinxdoc/source/_templates/orig/index.html
tests/documents/sphinxdoc/source/_templates/orig/indexsidebar.html
tests/documents/sphinxdoc/source/_templates/orig/layout.html
tests/documents/sphinxdoc/source/_templates/wuxi/index.html
tests/documents/sphinxdoc/source/_templates/wuxi/indexsidebar.html
tests/documents/sphinxdoc/source/_templates/wuxi/layout.html
tests/documents/sphinxdoc/source/_templates/wuxi/localtoc.html
tests/documents/sphinxdoc/source/ext/appapi.rst
tests/documents/sphinxdoc/source/ext/autodoc.rst
tests/documents/sphinxdoc/source/ext/autosummary.rst
tests/documents/sphinxdoc/source/ext/builderapi.rst
tests/documents/sphinxdoc/source/ext/coverage.rst
tests/documents/sphinxdoc/source/ext/doctest.rst
tests/documents/sphinxdoc/source/ext/extlinks.rst
tests/documents/sphinxdoc/source/ext/graphviz.rst
tests/documents/sphinxdoc/source/ext/ifconfig.rst
wuxi.egg-info/PKG-INFO
wuxi.egg-info/SOURCES.txt
wuxi.egg-info/dependency_links.txt
wuxi.egg-info/requires.txt
wuxi.egg-info/top_level.txt
