Metadata-Version: 1.0
Name: wuxi
Version: 0.1
Summary: Django template bridge and themes for Sphinx
Home-page: http://bitbucket.org/worrp/wuxi
Author: worrp
Author-email: contact@worrp.com
License: BSD
Download-URL: http://pypi.python.org/packages/source/w/wuxi/wuxi-0.1.tar.gz
Platform: UNKNOWN
Classifier: Development Status :: 1 - Planning
Classifier: Intended Audience :: Developers
Classifier: License :: OSI Approved :: BSD License
Classifier: Programming Language :: Python
Classifier: Framework :: Django
Classifier: Intended Audience :: Developers
Classifier: Topic :: Documentation
Classifier: Topic :: Software Development :: Documentation
